{
  "id": "3a6965a7-c09c-4104-87db-a14165277c9a",
  "prevId": "00000000-0000-0000-0000-000000000000",
  "version": "5",
  "dialect": "pg",
  "tables": {
    "activity": {
      "name": "activity",
      "schema": "",
      "columns": {
        "id": {
          "name": "id",
          "type": "text",
          "primaryKey": true,
          "notNull": true,
          "default": "generate_ulid()"
        },
        "action": {
          "name": "action",
          "type": "action",
          "primaryKey": false,
          "notNull": true
        },
        "actor_address": {
          "name": "actor_address",
          "type": "varchar",
          "primaryKey": false,
          "notNull": true
        },
        "target_address": {
          "name": "target_address",
          "type": "varchar",
          "primaryKey": false,
          "notNull": true
        },
        "action_timestamp": {
          "name": "action_timestamp",
          "type": "timestamp with time zone",
          "primaryKey": false,
          "notNull": true
        },
        "created_at": {
          "name": "created_at",
          "type": "timestamp with time zone",
          "primaryKey": false,
          "notNull": true,
          "default": "(now() AT TIME ZONE 'utc'::text)"
        },
        "updated_at": {
          "name": "updated_at",
          "type": "timestamp with time zone",
          "primaryKey": false,
          "notNull": true,
          "default": "(now() AT TIME ZONE 'utc'::text)"
        }
      },
      "indexes": {
        "index_activity_actor": {
          "name": "index_activity_actor",
          "columns": [
            "actor_address"
          ],
          "isUnique": false
        },
        "index_activity_target": {
          "name": "index_activity_target",
          "columns": [
            "target_address"
          ],
          "isUnique": false
        },
        "index_activity_action": {
          "name": "index_activity_action",
          "columns": [
            "action"
          ],
          "isUnique": false
        }
      },
      "foreignKeys": {
        "activity_actor_address_user_wallet_address_fk": {
          "name": "activity_actor_address_user_wallet_address_fk",
          "tableFrom": "activity",
          "tableTo": "user",
          "columnsFrom": [
            "actor_address"
          ],
          "columnsTo": [
            "wallet_address"
          ],
          "onDelete": "restrict",
          "onUpdate": "cascade"
        }
      },
      "compositePrimaryKeys": {},
      "uniqueConstraints": {}
    },
    "events": {
      "name": "events",
      "schema": "",
      "columns": {
        "id": {
          "name": "id",
          "type": "text",
          "primaryKey": true,
          "notNull": true,
          "default": "generate_ulid()"
        },
        "transaction_hash": {
          "name": "transaction_hash",
          "type": "varchar(66)",
          "primaryKey": false,
          "notNull": true
        },
        "block_number": {
          "name": "block_number",
          "type": "bigint",
          "primaryKey": false,
          "notNull": true
        },
        "contract_address": {
          "name": "contract_address",
          "type": "varchar(42)",
          "primaryKey": false,
          "notNull": true
        },
        "event_name": {
          "name": "event_name",
          "type": "varchar(255)",
          "primaryKey": false,
          "notNull": true
        },
        "event_parameters": {
          "name": "event_parameters",
          "type": "jsonb",
          "primaryKey": false,
          "notNull": true
        },
        "timestamp": {
          "name": "timestamp",
          "type": "timestamp with time zone",
          "primaryKey": false,
          "notNull": true
        },
        "processed": {
          "name": "processed",
          "type": "text",
          "primaryKey": false,
          "notNull": true,
          "default": "'false'"
        }
      },
      "indexes": {
        "idx_transaction_hash": {
          "name": "idx_transaction_hash",
          "columns": [
            "transaction_hash"
          ],
          "isUnique": false
        },
        "idx_contract_address": {
          "name": "idx_contract_address",
          "columns": [
            "contract_address"
          ],
          "isUnique": false
        },
        "idx_event_name": {
          "name": "idx_event_name",
          "columns": [
            "event_name"
          ],
          "isUnique": false
        },
        "idx_block_number": {
          "name": "idx_block_number",
          "columns": [
            "block_number"
          ],
          "isUnique": false
        }
      },
      "foreignKeys": {},
      "compositePrimaryKeys": {},
      "uniqueConstraints": {}
    },
    "user": {
      "name": "user",
      "schema": "",
      "columns": {
        "id": {
          "name": "id",
          "type": "text",
          "primaryKey": true,
          "notNull": true,
          "default": "generate_ulid()"
        },
        "wallet_address": {
          "name": "wallet_address",
          "type": "varchar",
          "primaryKey": false,
          "notNull": true
        },
        "created_at": {
          "name": "created_at",
          "type": "timestamp with time zone",
          "primaryKey": false,
          "notNull": true,
          "default": "(now() AT TIME ZONE 'utc'::text)"
        },
        "updated_at": {
          "name": "updated_at",
          "type": "timestamp with time zone",
          "primaryKey": false,
          "notNull": true,
          "default": "(now() AT TIME ZONE 'utc'::text)"
        }
      },
      "indexes": {},
      "foreignKeys": {},
      "compositePrimaryKeys": {},
      "uniqueConstraints": {
        "user_wallet_address_key": {
          "name": "user_wallet_address_key",
          "nullsNotDistinct": false,
          "columns": [
            "wallet_address"
          ]
        }
      }
    }
  },
  "enums": {
    "action": {
      "name": "action",
      "values": {
        "follow": "follow",
        "unfollow": "unfollow",
        "block": "block",
        "unblock": "unblock",
        "mute": "mute",
        "unmute": "unmute"
      }
    }
  },
  "schemas": {},
  "_meta": {
    "schemas": {},
    "tables": {},
    "columns": {}
  }
}